setup.cfg
setup.py
composite_form/__init__.py
composite_form/forms.py
django_composite_form.egg-info/PKG-INFO
django_composite_form.egg-info/SOURCES.txt
django_composite_form.egg-info/dependency_links.txt
django_composite_form.egg-info/top_level.txt
example/__init__.py
example/settings.py