Metadata-Version: 1.0
Name: django-composite-form
Version: 0.1.2
Summary: Helper class to handle form composition
Home-page: https://github.com/t0ster/django-composite-form
Author: Roman Dolgiy
Author-email: roman@bravetstudio.com
License: UNKNOWN
Platform: UNKNOWN
